odoo/addons/website_event_excerpt_img/README.rst
odoo/addons/website_event_excerpt_img/__init__.py
odoo/addons/website_event_excerpt_img/__manifest__.py
odoo/addons/website_event_excerpt_img/i18n/es.po
odoo/addons/website_event_excerpt_img/i18n/website_event_excerpt_img.pot
odoo/addons/website_event_excerpt_img/images/backend.png
odoo/addons/website_event_excerpt_img/images/customize.png
odoo/addons/website_event_excerpt_img/images/frontend.png
odoo/addons/website_event_excerpt_img/models/__init__.py
odoo/addons/website_event_excerpt_img/models/event.py
odoo/addons/website_event_excerpt_img/readme/CONFIGURE.rst
odoo/addons/website_event_excerpt_img/readme/CONTRIBUTORS.rst
odoo/addons/website_event_excerpt_img/readme/DESCRIPTION.rst
odoo/addons/website_event_excerpt_img/readme/INSTALL.rst
odoo/addons/website_event_excerpt_img/readme/USAGE.rst
odoo/addons/website_event_excerpt_img/static/description/icon.png
odoo/addons/website_event_excerpt_img/static/description/index.html
odoo/addons/website_event_excerpt_img/static/src/css/website_event_excerpt_img.scss
odoo/addons/website_event_excerpt_img/views/assets.xml
odoo/addons/website_event_excerpt_img/views/event.xml
odoo/addons/website_event_excerpt_img/views/event_event_view.xml
odoo12_addon_website_event_excerpt_img-12.0.1.2.0.dist-info/METADATA
odoo12_addon_website_event_excerpt_img-12.0.1.2.0.dist-info/WHEEL
odoo12_addon_website_event_excerpt_img-12.0.1.2.0.dist-info/top_level.txt
odoo12_addon_website_event_excerpt_img-12.0.1.2.0.dist-info/RECORD
