Metadata-Version: 2.1
Name: odoo12-addon-website-event-excerpt-img
Version: 12.0.1.2.0
Summary: New layout for event summary, including an excerpt and image
Home-page: https://github.com/OCA/event
Author: Tecnativa, Odoo Community Association (OCA)
Author-email: support@odoo-community.org
License: AGPL-3
Platform: UNKNOWN
Classifier: Programming Language :: Python
Classifier: Framework :: Odoo
Classifier: License :: OSI Approved :: GNU Affero General Public License v3
Requires-Python: >=3.5
Requires-Dist: odoo12-addon-html-image-url-extractor
Requires-Dist: odoo12-addon-html-text
Requires-Dist: odoo (<12.1dev,>=12.0a)
